odoo/addons/ssi_elearning_project/README.rst
odoo/addons/ssi_elearning_project/__init__.py
odoo/addons/ssi_elearning_project/__manifest__.py
odoo/addons/ssi_elearning_project/models/__init__.py
odoo/addons/ssi_elearning_project/models/slide_channel.py
odoo/addons/ssi_elearning_project/static/description/icon.png
odoo14_addon_ssi_elearning_project-14.0.1.0.1.dev3.dist-info/METADATA
odoo14_addon_ssi_elearning_project-14.0.1.0.1.dev3.dist-info/WHEEL
odoo14_addon_ssi_elearning_project-14.0.1.0.1.dev3.dist-info/top_level.txt
odoo14_addon_ssi_elearning_project-14.0.1.0.1.dev3.dist-info/RECORD
